clip/__init__.py
clip/model.py
clip/tokenizer.py
interpretdl/__init__.py
interpretdl/common/__init__.py
interpretdl/common/file_utils.py
interpretdl/common/paddle_utils.py
interpretdl/common/python_utils.py
interpretdl/data_processor/__init__.py
interpretdl/data_processor/readers.py
interpretdl/data_processor/visualizer.py
interpretdl/evaluate_interpreter/__init__.py
interpretdl/evaluate_interpreter/abc_evaluator.py
interpretdl/evaluate_interpreter/deletion_insertion.py
interpretdl/evaluate_interpreter/expo.py
interpretdl/evaluate_interpreter/infidelity.py
interpretdl/evaluate_interpreter/localization.py
interpretdl/evaluate_interpreter/perturbation.py
interpretdl/evaluate_models/__init__.py
interpretdl/evaluate_models/localization.py
interpretdl/incubator/__init__.py
interpretdl/incubator/influence_function.py
interpretdl/interpreter/__init__.py
interpretdl/interpreter/_global_prior_base.py
interpretdl/interpreter/_lime_base.py
interpretdl/interpreter/_normlime_base.py
interpretdl/interpreter/abc_interpreter.py
interpretdl/interpreter/abc_interpreter_m.py
interpretdl/interpreter/attention.py
interpretdl/interpreter/bidirectional_transformer.py
interpretdl/interpreter/consensus.py
interpretdl/interpreter/forgetting_events.py
interpretdl/interpreter/generic_attention.py
interpretdl/interpreter/glime.py
interpretdl/interpreter/gradient_cam.py
interpretdl/interpreter/gradient_shap.py
interpretdl/interpreter/influence_function.py
interpretdl/interpreter/integrated_gradients.py
interpretdl/interpreter/lime.py
interpretdl/interpreter/lime_prior.py
interpretdl/interpreter/lrp.py
interpretdl/interpreter/occlusion.py
interpretdl/interpreter/rollout.py
interpretdl/interpreter/score_cam.py
interpretdl/interpreter/smooth_grad.py
interpretdl/interpreter/smooth_grad_v2.py
interpretdl/interpreter/training_dynamics.py
interpretdl/interpreter/transition_attention_maps.py
tests/__init__.py
tests/test_common.py
tests/test_data_processor.py
tests/utils.py
interpretdl-0.8.0.dist-info/LICENSE
interpretdl-0.8.0.dist-info/METADATA
interpretdl-0.8.0.dist-info/WHEEL
interpretdl-0.8.0.dist-info/entry_points.txt
interpretdl-0.8.0.dist-info/top_level.txt
interpretdl-0.8.0.dist-info/RECORD
