Metadata-Version: 2.1
Name: interpretdl
Version: 0.8.0
Summary: interpretation of deep learning models
License: Apache 2.0
Keywords: interpreters for Paddle models
Classifier: Development Status :: 4 - Beta
Classifier: Intended Audience :: Developers
Classifier: Programming Language :: Python :: 3.7
Requires-Python: >=3.7.*
License-File: LICENSE
Requires-Dist: numpy
Requires-Dist: requests
Requires-Dist: scikit-image
Requires-Dist: scikit-learn (<=0.24)
Requires-Dist: tqdm
Requires-Dist: pillow
Requires-Dist: opencv-python
Requires-Dist: matplotlib
Requires-Dist: IPython
